mytest_zhangn35_20250918/__init__.py
mytest_zhangn35_20250918/main.py
mytest_zhangn35_20250918/py.typed
mytest_zhangn35_20250918-0.1.0.dist-info/WHEEL
mytest_zhangn35_20250918-0.1.0.dist-info/entry_points.txt
mytest_zhangn35_20250918-0.1.0.dist-info/METADATA
mytest_zhangn35_20250918-0.1.0.dist-info/RECORD
