Metadata-Version: 2.3
Name: mytest-zhangn35-20250918
Version: 0.1.0
Summary: Add your description here
Author: zhangning
Author-email: zhangning <zhangningshitiancai@gmail.com>
Requires-Dist: pip>=25.2
Requires-Python: >=3.12
